accim/__init__.py
accim/lists.py
accim/utils.py
accim/data/__init__.py
accim/data/morphing.py
accim/data/preprocessing.py
accim/data/postprocessing/__init__.py
accim/data/postprocessing/main.py
accim/data/postprocessing/utils.py
accim/parametric_and_optimisation/__init__.py
accim/parametric_and_optimisation/main.py
accim/parametric_and_optimisation/objectives.py
accim/parametric_and_optimisation/parameters.py
accim/parametric_and_optimisation/params_dicts.py
accim/parametric_and_optimisation/utils.py
accim/parametric_and_optimisation/funcs_for_besos/__init__.py
accim/parametric_and_optimisation/funcs_for_besos/param_accis.py
accim/parametric_and_optimisation/funcs_for_besos/param_apmv.py
accim/run/__init__.py
accim/run/run.py
accim/sample_files/__init__.py
accim/sample_files/jupyter_notebooks/__init__.py
accim/sample_files/jupyter_notebooks/Table/TestModel.idf
accim/sample_files/jupyter_notebooks/Table/TestModel[CS_INT EN16798[CA_1[CM_0[HM_2[VC_0[VO_0[MT_50[MW_50[AT_0.1[NS_X[United-Kingdom_Aberdeen_Present.csv
accim/sample_files/jupyter_notebooks/Table/TestModel[CS_INT EN16798[CA_1[CM_0[HM_2[VC_0[VO_0[MT_50[MW_50[AT_0.1[NS_X[United-Kingdom_London_Present.csv
accim/sample_files/jupyter_notebooks/Table/TestModel[CS_INT EN16798[CA_1[CM_3[HM_2[VC_0[VO_0[MT_50[MW_50[AT_0.1[NS_X[United-Kingdom_Aberdeen_Present.csv
accim/sample_files/jupyter_notebooks/Table/TestModel[CS_INT EN16798[CA_1[CM_3[HM_2[VC_0[VO_0[MT_50[MW_50[AT_0.1[NS_X[United-Kingdom_London_Present.csv
accim/sample_files/jupyter_notebooks/Table/TestModel[CS_INT EN16798[CA_2[CM_0[HM_2[VC_0[VO_0[MT_50[MW_50[AT_0.1[NS_X[United-Kingdom_Aberdeen_Present.csv
accim/sample_files/jupyter_notebooks/Table/TestModel[CS_INT EN16798[CA_2[CM_0[HM_2[VC_0[VO_0[MT_50[MW_50[AT_0.1[NS_X[United-Kingdom_London_Present.csv
accim/sample_files/jupyter_notebooks/Table/TestModel[CS_INT EN16798[CA_2[CM_3[HM_2[VC_0[VO_0[MT_50[MW_50[AT_0.1[NS_X[United-Kingdom_Aberdeen_Present.csv
accim-0.7.6.dist-info/licenses/LICENSE
accim-0.7.6.dist-info/METADATA
accim-0.7.6.dist-info/WHEEL
accim-0.7.6.dist-info/top_level.txt
accim-0.7.6.dist-info/RECORD
