Metadata-Version: 2.4
Name: accim
Version: 0.7.6
Summary: Transforms PMV-based into adaptive setpoint temperature EnergyPlus building energy models
Home-page: https://github.com/dsanchez-garcia/accim
Author: Daniel Sánchez-García
Author-email: daniel.sanchezgarcia@uca.es
License: GPL-3.0-or-later
Keywords: adaptive thermal comfort,building energy model,building performance simulation,energy efficiency
Classifier: Programming Language :: Python :: 3
Classifier: Intended Audience :: Science/Research
Classifier: Operating System :: Microsoft :: Windows
Classifier: Topic :: Scientific/Engineering
Requires-Python: <3.10
License-File: LICENSE
Requires-Dist: scikit-learn
Requires-Dist: eppy>=0.5.63
Requires-Dist: pycountry
Requires-Dist: matplotlib<=3.7
Requires-Dist: numpy<2.0.0
Requires-Dist: pandas
Requires-Dist: datapackage
Requires-Dist: unidecode
Requires-Dist: besos
Dynamic: author
Dynamic: author-email
Dynamic: classifier
Dynamic: description
Dynamic: description-content-type
Dynamic: home-page
Dynamic: keywords
Dynamic: license
Dynamic: license-file
Dynamic: requires-dist
Dynamic: requires-python
Dynamic: summary
